teslajsonpy2/BatterySensor.py
teslajsonpy2/BinarySensor.py
teslajsonpy2/Charger.py
teslajsonpy2/Climate.py
teslajsonpy2/Exceptions.py
teslajsonpy2/GPS.py
teslajsonpy2/Lock.py
teslajsonpy2/Trunk.py
teslajsonpy2/__init__.py
teslajsonpy2/connection.py
teslajsonpy2/controller.py
teslajsonpy2/vehicle.py
teslajsonpy2/__pycache__/BatterySensor.cpython-36.pyc
teslajsonpy2/__pycache__/BinarySensor.cpython-36.pyc
teslajsonpy2/__pycache__/Charger.cpython-36.pyc
teslajsonpy2/__pycache__/Climate.cpython-36.pyc
teslajsonpy2/__pycache__/Exceptions.cpython-36.pyc
teslajsonpy2/__pycache__/GPS.cpython-36.pyc
teslajsonpy2/__pycache__/Lock.cpython-36.pyc
teslajsonpy2/__pycache__/Trunk.cpython-36.pyc
teslajsonpy2/__pycache__/__init__.cpython-36.pyc
teslajsonpy2/__pycache__/connection.cpython-36.pyc
teslajsonpy2/__pycache__/controller.cpython-36.pyc
teslajsonpy2/__pycache__/vehicle.cpython-36.pyc
teslajsonpy2-0.1.24.dist-info/METADATA
teslajsonpy2-0.1.24.dist-info/RECORD
teslajsonpy2-0.1.24.dist-info/WHEEL
teslajsonpy2-0.1.24.dist-info/top_level.txt
